ostats.py
ostats-2023.3.23.dist-info/LICENSE
ostats-2023.3.23.dist-info/WHEEL
ostats-2023.3.23.dist-info/METADATA
ostats-2023.3.23.dist-info/RECORD
