Metadata-Version: 2.1
Name: ostats
Version: 2023.3.23
Summary: online algorithm for mean, variance, and covariance
Keywords: online algorithm,online mean,online variance,online covariance,online statistics
Author-email: Nicolas Tessore <n.tessore@ucl.ac.uk>
Requires-Python: >=3.6
Classifier: License :: OSI Approved :: MIT License
Project-URL: Home, https://github.com/ntessore/ostats
Project-URL: Issues, https://github.com/ntessore/ostats/issues
